pdcst/__init__.py
pdcst/config.py
pdcst/download.py
pdcst/models.py
pdcst/repository.py
pdcst-0.11.dist-info/entry_points.txt
pdcst-0.11.dist-info/LICENSE
pdcst-0.11.dist-info/WHEEL
pdcst-0.11.dist-info/METADATA
pdcst-0.11.dist-info/RECORD
